[
    {
        "name": "Ernesto Gomez",
        "initials": "EG",
        "text":
            "DJ Boots did an awesome job. The music was great and he had us on our feet dancing all night! I highly recommend DJ Boots. 5 star rating :star:. Thank you DJ Boots",
        "location": "Indio, CA",
        "image": ""
    },
    {
        "name": "Ruben Guzman",
        "initials": "RG",
        "text":
            "Had the honor of helping coordinate a huge event this weekend. I have to say DJ Boots was amazing! 5 star service. Book him for your next event.",
        "location": "Bermuda Dunes, CA",
        "image": "assets/images/ruben-guzman.jpg"
    }
]
